django_polymorphic_auth-0.4.dist-info/DESCRIPTION.rst
django_polymorphic_auth-0.4.dist-info/METADATA
django_polymorphic_auth-0.4.dist-info/RECORD
django_polymorphic_auth-0.4.dist-info/WHEEL
django_polymorphic_auth-0.4.dist-info/metadata.json
django_polymorphic_auth-0.4.dist-info/top_level.txt
polymorphic_auth/__init__.py
polymorphic_auth/admin.py
polymorphic_auth/apps.py
polymorphic_auth/appsettings.py
polymorphic_auth/models.py
polymorphic_auth/monkey.py
polymorphic_auth/views.py
polymorphic_auth/migrations/0001_initial.py
polymorphic_auth/migrations/0002_auto_20160725_2124.py
polymorphic_auth/migrations/__init__.py
polymorphic_auth/plugins/__init__.py
polymorphic_auth/plugins/base.py
polymorphic_auth/tests/__init__.py
polymorphic_auth/tests/settings.py
polymorphic_auth/tests/tests.py
polymorphic_auth/tests/urls.py
polymorphic_auth/usertypes/__init__.py
polymorphic_auth/usertypes/email/__init__.py
polymorphic_auth/usertypes/email/admin.py
polymorphic_auth/usertypes/email/apps.py
polymorphic_auth/usertypes/email/models.py
polymorphic_auth/usertypes/email/polymorphic_auth_plugins.py
polymorphic_auth/usertypes/email/migrations/0001_initial.py
polymorphic_auth/usertypes/email/migrations/__init__.py
polymorphic_auth/usertypes/username/__init__.py
polymorphic_auth/usertypes/username/admin.py
polymorphic_auth/usertypes/username/apps.py
polymorphic_auth/usertypes/username/models.py
polymorphic_auth/usertypes/username/polymorphic_auth_plugins.py
polymorphic_auth/usertypes/username/migrations/0001_initial.py
polymorphic_auth/usertypes/username/migrations/__init__.py
