Metadata-Version: 2.0
Name: django-polymorphic-auth
Version: 0.4
Summary: Polymorphic user model with plugins for common options, plus abstract and mixin classes to create your own.
Home-page: https://github.com/ixc/django-polymorphic-auth
Author: Interaction Consortium
Author-email: studio@interaction.net.au
License: MIT
Platform: UNKNOWN
Requires-Dist: Django
Requires-Dist: django-polymorphic
Provides-Extra: dev
Requires-Dist: ipdb; extra == 'dev'
Requires-Dist: ipython; extra == 'dev'
Provides-Extra: test
Requires-Dist: WebTest; extra == 'test'
Requires-Dist: coverage; extra == 'test'
Requires-Dist: django-dynamic-fixture; extra == 'test'
Requires-Dist: django-nose; extra == 'test'
Requires-Dist: django-webtest; extra == 'test'
Requires-Dist: nose-progressive; extra == 'test'
